Workbook

Sheet Assumptions
A1: LeadGen AI Voice Agent — Unit Economics Model
A2: Neeli (blue) cells = badlo. Kaali = auto-calculate. Yellow = key input.
A4: TELEPHONY (call cost)
A5: Average call duration | B5: 3 | C5: minutes per call (typical AI lead call)
A6: Per-minute telephony rate | B6: 0.4 | C6: ₹/min — cheapest India SIP trunk (₹0.30–0.50)
A7: → Telephony cost per call | B7: =B5*B6 -> 1.2 | C7: auto = duration × per-min rate
A9: CALLING VOLUME & CONVERSION
A10: Calls per client / month | B10: 1000 | C10: kitni calls ek client ke liye
A11: Lead conversion rate | B11: 0.04 | C11: % calls jo qualified lead bante hain (3–5% typical)
A12: → Qualified leads / client / month | B12: =B10*B11 -> 40 | C12: auto = calls × conversion
A14: PRICING (tum client se kya lete ho)
A15: Price per qualified lead | B15: 300 | C15: ₹/lead — recommended ₹200–500
A16: OR flat 'unlimited' fee / client | B16: 5000 | C16: agar 'free unlimited calls' becho (TRAP — neeche dekho)
A18: FIXED COSTS (monthly)
A19: Hosting / VPS | B19: 500 | C19: shared — self-host server
A20: AI / LLM / STT / TTS | B20: 0 | C20: free tier (Whisper+EdgeTTS+Gemini) = ₹0
A21: SIP channel rental / client | B21: 1149 | C21: flat per client (FreJun-style) — ya 0 agar pure per-min
A23: SCALE
A24: Number of clients | B24: 10 | C24: kitni companies tumhari client hain

Sheet Per-Client P&L
A1: Per-Client P&L (ek client, ek month)
A3: Calls / month | B3: =Assumptions!B10 -> 1000
A4: Qualified leads | B4: =Assumptions!B12 -> 40
A5: Revenue (per-lead model) | B5: =Assumptions!B12*Assumptions!B15 -> 12000 | C5: leads × price/lead
A6: Telephony cost | B6: =Assumptions!B10*Assumptions!B7 -> 1200 | C6: calls × cost/call
A7: SIP channel rental | B7: =Assumptions!B21 -> 1149 | C7: flat per client
A8: Cost to serve | B8: =B6+B7 -> 2349 | C8: telephony + SIP
A9: Gross profit / client | B9: =B5-B8 -> 9651 | C9: revenue − cost
A10: Gross margin | B10: =IF(B5=0,0,B9/B5) -> 0.80425
A12: Note: telephony cost (₹~) revenue ke saamne kitna chhota hai — yahi point hai.

Sheet At-Scale P&L
A1: At-Scale P&L (sabhi clients milake, monthly)
A3: Number of clients | B3: =Assumptions!B24 -> 10
A4: Total calls / month | B4: =B3*Assumptions!B10 -> 10000 | C4: clients × calls each
A5: Total qualified leads | B5: =B3*Assumptions!B12 -> 400
A6: Total revenue | B6: =B5*Assumptions!B15 -> 120000 | C6: per-lead model
A7: Total telephony cost | B7: =B4*Assumptions!B7 -> 12000 | C7: scales with calls
A8: Total SIP rentals | B8: =B3*Assumptions!B21 -> 11490 | C8: per client
A9: Fixed costs (hosting+AI) | B9: =Assumptions!B19+Assumptions!B20 -> 500 | C9: shared, one-time monthly
A10: Total cost | B10: =B7+B8+B9 -> 23990
A11: NET PROFIT / month | B11: =B6-B10 -> 96010 | C11: revenue − total cost
A12: Net margin | B12: =IF(B6=0,0,B11/B6) -> 0.80008333
A13: Profit per client | B13: =IF(B3=0,0,B11/B3) -> 9601
A14: Telephony as % of revenue | B14: =IF(B6=0,0,B7/B6) -> 0.1 | C14: ← dekho kitna chhota hai
A16: KEY: jaise clients badhte hain, cost AUR revenue dono badhte hain — profit bhi. Per-call doobata nahi.

Sheet Free-vs-PerLead
A1: 'Free unlimited' becho vs 'Per-lead' becho — kya farak
A3: (per client / month) | B3: Model A: FREE unlimited | C3: Model B: PER-LEAD
A4: Calls / month | B4: =Assumptions!B10 -> 1000 | C4: =Assumptions!B10 -> 1000 | D4: same volume
A5: Revenue | B5: =Assumptions!B16 -> 5000 | C5: =Assumptions!B12*Assumptions!B15 -> 12000 | D5: A=flat fee, B=per lead
A6: Telephony cost | B6: =Assumptions!B10*Assumptions!B7 -> 1200 | C6: =Assumptions!B10*Assumptions!B7 -> 1200 | D6: dono me same
A7: SIP rental | B7: =Assumptions!B21 -> 1149 | C7: =Assumptions!B21 -> 1149
A8: Profit / client | B8: =B5-B6-B7 -> 2651 | C8: =C5-C6-C7 -> 9651
A10: Ab Assumptions me 'Calls per client' 1000 se 4000 kar do →
A11: Model A (free): calls badhne se telephony badhega par revenue flat → profit GIRTA hai, loss me ja sakta hai.
A12: Model B (per-lead): calls badhne se leads badhte hain → revenue bhi badhta hai → profit BADHTA hai.
A13: Isiliye 'free calls' becho mat — PER-LEAD becho. Yahi tumhe doobne se bachata hai.

Sheet Scenarios
A1: Scenario table — clients badhao, profit dekho
A2: Clients | B2: Total calls | C2: Total leads | D2: Revenue | E2: Telephony | F2: SIP rental | G2: Fixed | H2: Net profit | I2: Margin
A3: 1 | B3: =A3*Assumptions!$B$10 -> 1000 | C3: =A3*Assumptions!$B$12 -> 40 | D3: =C3*Assumptions!$B$15 -> 12000 | E3: =B3*Assumptions!$B$7 -> 1200 | F3: =A3*Assumptions!$B$21 -> 1149 | G3: =Assumptions!$B$19+Assumptions!$B$20 -> 500 | H3: =D3-E3-F3-G3 -> 9151 | I3: =IF(D3=0,0,H3/D3) -> 0.76258333
A4: 5 | B4: =A4*Assumptions!$B$10 -> 5000 | C4: =A4*Assumptions!$B$12 -> 200 | D4: =C4*Assumptions!$B$15 -> 60000 | E4: =B4*Assumptions!$B$7 -> 6000 | F4: =A4*Assumptions!$B$21 -> 5745 | G4: =Assumptions!$B$19+Assumptions!$B$20 -> 500 | H4: =D4-E4-F4-G4 -> 47755 | I4: =IF(D4=0,0,H4/D4) -> 0.79591667
A5: 10 | B5: =A5*Assumptions!$B$10 -> 10000 | C5: =A5*Assumptions!$B$12 -> 400 | D5: =C5*Assumptions!$B$15 -> 120000 | E5: =B5*Assumptions!$B$7 -> 12000 | F5: =A5*Assumptions!$B$21 -> 11490 | G5: =Assumptions!$B$19+Assumptions!$B$20 -> 500 | H5: =D5-E5-F5-G5 -> 96010 | I5: =IF(D5=0,0,H5/D5) -> 0.80008333
A6: 25 | B6: =A6*Assumptions!$B$10 -> 25000 | C6: =A6*Assumptions!$B$12 -> 1000 | D6: =C6*Assumptions!$B$15 -> 300000 | E6: =B6*Assumptions!$B$7 -> 30000 | F6: =A6*Assumptions!$B$21 -> 28725 | G6: =Assumptions!$B$19+Assumptions!$B$20 -> 500 | H6: =D6-E6-F6-G6 -> 240775 | I6: =IF(D6=0,0,H6/D6) -> 0.80258333
A7: 50 | B7: =A7*Assumptions!$B$10 -> 50000 | C7: =A7*Assumptions!$B$12 -> 2000 | D7: =C7*Assumptions!$B$15 -> 600000 | E7: =B7*Assumptions!$B$7 -> 60000 | F7: =A7*Assumptions!$B$21 -> 57450 | G7: =Assumptions!$B$19+Assumptions!$B$20 -> 500 | H7: =D7-E7-F7-G7 -> 482050 | I7: =IF(D7=0,0,H7/D7) -> 0.80341667
A8: 100 | B8: =A8*Assumptions!$B$10 -> 100000 | C8: =A8*Assumptions!$B$12 -> 4000 | D8: =C8*Assumptions!$B$15 -> 1200000 | E8: =B8*Assumptions!$B$7 -> 120000 | F8: =A8*Assumptions!$B$21 -> 114900 | G8: =Assumptions!$B$19+Assumptions!$B$20 -> 500 | H8: =D8-E8-F8-G8 -> 964600 | I8: =IF(D8=0,0,H8/D8) -> 0.80383333
A9: 250 | B9: =A9*Assumptions!$B$10 -> 250000 | C9: =A9*Assumptions!$B$12 -> 10000 | D9: =C9*Assumptions!$B$15 -> 3000000 | E9: =B9*Assumptions!$B$7 -> 300000 | F9: =A9*Assumptions!$B$21 -> 287250 | G9: =Assumptions!$B$19+Assumptions!$B$20 -> 500 | H9: =D9-E9-F9-G9 -> 2412250 | I9: =IF(D9=0,0,H9/D9) -> 0.80408333
A11: Numbers Assumptions sheet se aate hain — wahan kuch bhi badlo, ye table update ho jaayega.
